akima86/__init__.py
akima86/akima86.py
akima86/uvipia_omp.cpython-39-x86_64-linux-gnu.so
akima86.libs/libgfortran-8f1e9814.so.5.0.0
akima86.libs/libgomp-870cb1d0.so.1.0.0
akima86.libs/libquadmath-828275a7.so.0.0.0
akima86-0.1.1.dist-info/METADATA
akima86-0.1.1.dist-info/WHEEL
akima86-0.1.1.dist-info/RECORD
